ObjectListView/CellEditor.py
ObjectListView/Filter.py
ObjectListView/ListCtrlPrinter.py
ObjectListView/ObjectListView.py
ObjectListView/OLVEvent.py
ObjectListView/OLVPrinter.py
ObjectListView/WordWrapRenderer.py
ObjectListView/__init__.py
ObjectListView-1.3.1.dist-info/DESCRIPTION.rst
ObjectListView-1.3.1.dist-info/METADATA
ObjectListView-1.3.1.dist-info/metadata.json
ObjectListView-1.3.1.dist-info/RECORD
ObjectListView-1.3.1.dist-info/top_level.txt
ObjectListView-1.3.1.dist-info/WHEEL
