Metadata-Version: 2.0
Name: ObjectListView
Version: 1.3.1
Summary: An ObjectListView is a wrapper around the wx.ListCtrl that makes the list control easier to use
Home-page: https://bitbucket.org/wbruhin/objectlistview
Author: Phillip Piper
Author-email: phillip.piper@gmail.com
License: wxWindows
Download-URL: https://bitbucket.org/wbruhin/objectlistview/downloads
Platform: Many
Classifier: Development Status :: 4 - Beta
Classifier: Intended Audience :: Developers
Classifier: Topic :: Software Development :: User Interfaces
